README.md
setup.py
qudoor/__init__.py
qudoor.egg-info/PKG-INFO
qudoor.egg-info/SOURCES.txt
qudoor.egg-info/dependency_links.txt
qudoor.egg-info/requires.txt
qudoor.egg-info/top_level.txt
qudoor/core/QubitArray.py
qudoor/core/__init__.py
qudoor/core/constants.py
qudoor/core/gate.py
qudoor/core/meta_qubit.py
qudoor/core/method.py
qudoor/core/qubit.py