Metadata-Version: 2.1
Name: qudoor
Version: 5.2
Requires-Dist: numpy
Requires-Dist: matplotlib
Requires-Dist: scipy
